[
    {
        "timestamp": "2025-03-30 18:03:58",
        "mode": "AI",
        "trial_duration": 0.0,
        "trial_outcome": "manual_reset",
        "goal_reached": null,
        "trajectory": [
            [
                799.8032498646396,
                398.1983286509535,
                0.34804617072801636
            ],
            [
                799.3513547155248,
                398.4842772293584,
                0.3814683230195894
            ],
            [
                798.8783292902947,
                397.14422591564653,
                0.3651125117420867
            ],
            [
                800.2689699388211,
                395.3263590812561,
                0.3562291901155546
            ],
            [
                800.1832919372972,
                393.5111158192599,
                0.36845608648096584
            ],
            [
                801.6536779171722,
                394.4422343136626,
                0.383011737922988
            ],
            [
                803.1322549099618,
                392.32679568172153,
                0.36067034656095426
            ],
            [
                805.6685385346251,
                390.6996212502738,
                0.36235284746110036
            ],
            [
                807.3897266795325,
                392.49710668873206,
                0.3110159619757909
            ],
            [
                806.1592982413936,
                391.71432167102006,
                0.3391669340358612
            ],
            [
                805.0623381542423,
                390.34057073241394,
                0.35336110081510547
            ],
            [
                807.8408031792072,
                387.5833485103429,
                0.3396815162742314
            ],
            [
                809.8931657591702,
                385.65022965860805,
                0.33762158316405005
            ]
        ]
    }
]